huelights/__init__.py
huelights/bridge.py
huelights/light.py
huelights/utils.py
huelights-0.1.1.dist-info/LICENSE
huelights-0.1.1.dist-info/METADATA
huelights-0.1.1.dist-info/WHEEL
huelights-0.1.1.dist-info/top_level.txt
huelights-0.1.1.dist-info/RECORD
