Metadata-Version: 2.1
Name: huelights
Version: 0.1.1
Summary: A Python wrapper to interact with Philips Hue smart lights
Home-page: https://github.com/zackelia/huelights
Author: Zack Elia
Author-email: pypi@zacharyelia.com
License: UNKNOWN
Platform: UNKNOWN
Classifier: Programming Language :: Python :: 3.7
Classifier: License :: OSI Approved :: GNU General Public License v3 (GPLv3)
Classifier: Operating System :: OS Independent
